aiobookoo/__init__.py
aiobookoo/bookooscale.py
aiobookoo/const.py
aiobookoo/decode.py
aiobookoo/exceptions.py
aiobookoo/helpers.py
aiobookoo/py.typed
aiobookoo-0.1.0.dist-info/LICENSE
aiobookoo-0.1.0.dist-info/METADATA
aiobookoo-0.1.0.dist-info/WHEEL
aiobookoo-0.1.0.dist-info/top_level.txt
aiobookoo-0.1.0.dist-info/RECORD
