Metadata-Version: 2.2
Name: aiobookoo
Version: 0.1.0
Summary: A bookoo port of aioacaia
Author-email: Makerwolf <160181889+makerwolf@users.noreply.github.com>
Maintainer-email: Makerwolf <160181889+makerwolf@users.noreply.github.com>
License: MIT
Project-URL: Homepage, https://github.com/makerwolf/aiobookoo
Project-URL: Repository, https://github.com/makerwolf/aiobookoo
Project-URL: Documentation, https://github.com/makerwolf/aiobookoo
Keywords: Bookoo,Bluetooth,api,async,client
Classifier: Development Status :: 4 - Beta
Classifier: Framework :: AsyncIO
Classifier: Intended Audience :: Developers
Classifier: Natural Language :: English
Classifier: License :: OSI Approved :: MIT License
Classifier: Programming Language :: Python
Classifier: Programming Language :: Python :: 3.12
Requires-Python: >=3.12
License-File: LICENSE
Requires-Dist: bleak>=0.20.2
Provides-Extra: dev
Requires-Dist: covdefaults==2.3.0; extra == "dev"
Requires-Dist: coverage==7.6.7; extra == "dev"
Requires-Dist: syrupy==4.7.2; extra == "dev"
Requires-Dist: pytest==8.3.3; extra == "dev"
Requires-Dist: pytest-asyncio==0.24.0; extra == "dev"
Requires-Dist: pytest-cov==6.0.0; extra == "dev"
